judoscale/__init__.py
judoscale/asgi/__init__.py
judoscale/asgi/middleware.py
judoscale/celery/__init__.py
judoscale/celery/collector.py
judoscale/core/__init__.py
judoscale/core/adapter.py
judoscale/core/config.py
judoscale/core/logger.py
judoscale/core/metric.py
judoscale/core/metrics_collectors.py
judoscale/core/metrics_store.py
judoscale/core/reporter.py
judoscale/core/utilization_tracker.py
judoscale/django/__init__.py
judoscale/django/apps.py
judoscale/django/middleware.py
judoscale/django/redis.py
judoscale/flask/__init__.py
judoscale/flask/judoscale.py
judoscale/rq/__init__.py
judoscale/rq/apps.py
judoscale/rq/collector.py
judoscale-1.10.2.dist-info/LICENSE
judoscale-1.10.2.dist-info/WHEEL
judoscale-1.10.2.dist-info/METADATA
judoscale-1.10.2.dist-info/RECORD
