Metadata-Version: 2.1
Name: judoscale
Version: 1.10.2
Summary: Official Python adapter for Judoscale — the advanced autoscaler for Heroku
Home-page: https://github.com/judoscale/judoscale-python
License: MIT
Author: Adam McCrea
Author-email: adam@adamlogic.com
Requires-Python: >=3.8,<4.0
Classifier: License :: OSI Approved :: MIT License
Classifier: Operating System :: OS Independent
Classifier: Programming Language :: Python :: 3
Classifier: Programming Language :: Python :: 3.8
Classifier: Programming Language :: Python :: 3.9
Classifier: Programming Language :: Python :: 3.10
Classifier: Programming Language :: Python :: 3.11
Classifier: Programming Language :: Python :: 3
Provides-Extra: asgi
Provides-Extra: celery-redis
Provides-Extra: django
Provides-Extra: flask
Provides-Extra: rq
Requires-Dist: celery[redis] (>=4.4.0,<6.0.0); extra == "celery-redis"
Requires-Dist: django (>=2.1.0,<6.0.0); extra == "django"
Requires-Dist: flask (>=1.1.0,<4.0.0); extra == "flask"
Requires-Dist: requests (<3.0.0)
Requires-Dist: rq (>=1.0.0,<2.0.0); extra == "rq"
Project-URL: Repository, https://github.com/judoscale/judoscale-python
